src/__init__.py
src/cli/__init__.py
src/cli/aggregate_metrics.py
src/cli/cli.py
src/cli/parsers.py
src/cli/utils.py
src/cli/commands/__init__.py
src/cli/commands/cmd_calculate.py
src/cli/commands/cmd_diff.py
src/cli/commands/cmd_extract.py
src/cli/commands/cmd_init.py
src/cli/commands/cmd_list.py
src/cli/commands/cmd_norm_diff.py
src/cli/exceptions/__init__.py
src/cli/exceptions/exceptions.py
src/cli/jsonReader/__init__.py
src/cli/jsonReader/jsonReader.py
src/cli/resources/__init__.py
src/cli/resources/characteristic.py
src/cli/resources/measure.py
src/cli/resources/metrics.py
src/cli/resources/perf_eff_measure.py
src/cli/resources/perf_eff_parser.py
src/cli/resources/subcharacteristic.py
src/cli/resources/tsqmi.py
src/config/__init__.py
src/config/settings.py
src/config/setup_log.py
tests/__init__.py
tests/system/__init__.py
tests/system/test_extract.py
tests/system/test_help.py
tests/system/test_init.py
tests/system/test_list.py
tests/unit/__init__.py
tests/unit/test_aggregate.py
tests/unit/test_calculate.py
tests/unit/test_characteristic.py
tests/unit/test_diff.py
tests/unit/test_extract.py
tests/unit/test_init.py
tests/unit/test_jsonReader.py
tests/unit/test_list.py
tests/unit/test_measures.py
tests/unit/test_norm_diff.py
tests/unit/test_parser.py
tests/unit/test_setup_log.py
tests/unit/test_subcharacteristic.py
tests/unit/test_tsqmi.py
tests/unit/data/file_reader_response.py
msgram-3.3.0.dist-info/LICENSE
msgram-3.3.0.dist-info/METADATA
msgram-3.3.0.dist-info/WHEEL
msgram-3.3.0.dist-info/entry_points.txt
msgram-3.3.0.dist-info/top_level.txt
msgram-3.3.0.dist-info/RECORD
