Metadata-Version: 2.1
Name: msgram
Version: 3.3.0
Summary: The msgram CLI is a command-line interface to use MeasureSoftGram software
Author-email: MeasureSoftGram <measuresoftgram@gmail.com>
License: GNU AFFERO GENERAL PUBLIC LICENSE
Keywords: core,measures,quality,algebraic model
Classifier: Environment :: Console
Classifier: License :: OSI Approved :: GNU Affero General Public License v3 or later (AGPLv3+)
Classifier: Natural Language :: Portuguese (Brazilian)
Classifier: Operating System :: OS Independent
Classifier: Programming Language :: Python :: 3.8
Classifier: Topic :: Utilities
Requires-Python: >=3.9
License-File: LICENSE
Requires-Dist: requests ~=2.32.3
Requires-Dist: pytz
Requires-Dist: typing ~=3.7.4.3
Requires-Dist: tabulate ~=0.9.0
Requires-Dist: termcolor ~=2.4.0
Requires-Dist: pandas ~=2.2.2
Requires-Dist: setuptools ~=72.1.0
Requires-Dist: python-dotenv
Requires-Dist: rich
Requires-Dist: validators ~=0.33.0
Requires-Dist: msgram-core ~=1.5.3
Requires-Dist: msgram-parser ~=1.2.1
Requires-Dist: anytree
Provides-Extra: dev
Requires-Dist: pytest ; extra == 'dev'
Requires-Dist: pytest-cov ; extra == 'dev'
Requires-Dist: setuptools ; extra == 'dev'
Requires-Dist: wheel ; extra == 'dev'
